[
    {
        "user_id": 1,
        "first_name": "Harp",
        "last_name": "Tribbeck",
        "email": "htribbeck0@indiegogo.com",
        "gender": "Male",
        "birthdate": "7/26/1964",
        "address": "10079 Green Lane",
        "city": "Saint-Raymond",
        "country": "Canada",
        "phone_number": "226-158-6064"
    },
    {
        "user_id": 2,
        "first_name": "Jennie",
        "last_name": "Petyanin",
        "email": "jpetyanin1@hatena.ne.jp",
        "gender": "Female",
        "birthdate": "2/13/1963",
        "address": "82 Donald Hill",
        "city": "Lodan Wetan",
        "country": "Indonesia",
        "phone_number": "182-733-0212"
    },
    {
        "user_id": 3,
        "first_name": "Rawley",
        "last_name": "Farrall",
        "email": "rfarrall2@oaic.gov.au",
        "gender": "Male",
        "birthdate": "6/25/1986",
        "address": "471 Sutherland Crossing",
        "city": "Yajiang",
        "country": "China",
        "phone_number": "894-795-7826"
    },
    {
        "user_id": 4,
        "first_name": "Fay",
        "last_name": "McGeneay",
        "email": "fmcgeneay3@wunderground.com",
        "gender": "Female",
        "birthdate": "2/7/1970",
        "address": "569 Rockefeller Terrace",
        "city": "Jiujiang",
        "country": "China",
        "phone_number": "762-783-9275"
    },
    {
        "user_id": 5,
        "first_name": "Marina",
        "last_name": "Heinig",
        "email": "mheinig4@webmd.com",
        "gender": "Female",
        "birthdate": "9/28/1966",
        "address": "17661 Schurz Way",
        "city": "Voskhod",
        "country": "Ukraine",
        "phone_number": "307-374-7164"
    },
    {
        "user_id": 6,
        "first_name": "Curtis",
        "last_name": "Huge",
        "email": "chuge5@craigslist.org",
        "gender": "Male",
        "birthdate": "3/6/1958",
        "address": "39541 Forster Trail",
        "city": "Gaozhuang",
        "country": "China",
        "phone_number": "211-961-9573"
    },
    {
        "user_id": 7,
        "first_name": "Terence",
        "last_name": "Wharin",
        "email": "twharin6@alexa.com",
        "gender": "Male",
        "birthdate": "12/25/1994",
        "address": "22 Walton Terrace",
        "city": "Marija Bistrica",
        "country": "Croatia",
        "phone_number": "983-718-2068"
    },
    {
        "user_id": 8,
        "first_name": "Jeffy",
        "last_name": "Tripp",
        "email": "jtripp7@vimeo.com",
        "gender": "Male",
        "birthdate": "6/7/1990",
        "address": "4926 Rowland Park",
        "city": "Santa Catarina Barahona",
        "country": "Guatemala",
        "phone_number": "439-620-7943"
    },
    {
        "user_id": 9,
        "first_name": "Blakeley",
        "last_name": "Michurin",
        "email": "bmichurin8@oracle.com",
        "gender": "Female",
        "birthdate": "1/4/1963",
        "address": "41 Golf Course Alley",
        "city": "Jundian",
        "country": "China",
        "phone_number": "651-923-6271"
    },
    {
        "user_id": 10,
        "first_name": "Quintilla",
        "last_name": "Budd",
        "email": "qbudd9@cdbaby.com",
        "gender": "Female",
        "birthdate": "3/12/1950",
        "address": "647 Springs Circle",
        "city": "Gorgoram",
        "country": "Nigeria",
        "phone_number": "143-280-4207"
    },
    {
        "user_id": 11,
        "first_name": "Jolyn",
        "last_name": "O' Dornan",
        "email": "jodornana@plala.or.jp",
        "gender": "Female",
        "birthdate": "12/16/2002",
        "address": "74 Lindbergh Way",
        "city": "Budapest",
        "country": "Hungary",
        "phone_number": "104-790-1683"
    },
    {
        "user_id": 12,
        "first_name": "Courtney",
        "last_name": "Harcombe",
        "email": "charcombeb@joomla.org",
        "gender": "Male",
        "birthdate": "11/13/1954",
        "address": "7291 Calypso Street",
        "city": "Church End",
        "country": "United Kingdom",
        "phone_number": "390-876-8220"
    },
    {
        "user_id": 13,
        "first_name": "Harrie",
        "last_name": "Boddam",
        "email": "hboddamc@businesswire.com",
        "gender": "Female",
        "birthdate": "12/14/1982",
        "address": "56 Marcy Trail",
        "city": "Dongfeng",
        "country": "China",
        "phone_number": "701-671-7464"
    },
    {
        "user_id": 14,
        "first_name": "Fairlie",
        "last_name": "Nalder",
        "email": "fnalderd@addthis.com",
        "gender": "Male",
        "birthdate": "12/8/2000",
        "address": "985 Kinsman Avenue",
        "city": "Ruse",
        "country": "Bulgaria",
        "phone_number": "835-621-9908"
    },
    {
        "user_id": 15,
        "first_name": "Fara",
        "last_name": "Tullot",
        "email": "ftullote@chronoengine.com",
        "gender": "Female",
        "birthdate": "4/9/1981",
        "address": "04 Kedzie Park",
        "city": "Filipowice",
        "country": "Poland",
        "phone_number": "858-977-7051"
    },
    {
        "user_id": 16,
        "first_name": "Jaime",
        "last_name": "Libri",
        "email": "jlibrif@google.es",
        "gender": "Female",
        "birthdate": "1/1/1951",
        "address": "06 Bartelt Terrace",
        "city": "Guisa",
        "country": "Cuba",
        "phone_number": "633-705-7827"
    },
    {
        "user_id": 17,
        "first_name": "Lorilee",
        "last_name": "Skiplorne",
        "email": "lskiplorneg@odnoklassniki.ru",
        "gender": "Female",
        "birthdate": "1/7/1974",
        "address": "2 Golf View Avenue",
        "city": "Gendiwu",
        "country": "Indonesia",
        "phone_number": "340-826-1965"
    },
    {
        "user_id": 18,
        "first_name": "Ewan",
        "last_name": "Lambillion",
        "email": "elambillionh@reuters.com",
        "gender": "Bigender",
        "birthdate": "5/30/1977",
        "address": "68476 Hoepker Trail",
        "city": "Buga",
        "country": "Colombia",
        "phone_number": "747-978-6568"
    },
    {
        "user_id": 19,
        "first_name": "Ring",
        "last_name": "Kenaway",
        "email": "rkenawayi@stumbleupon.com",
        "gender": "Male",
        "birthdate": "3/31/1958",
        "address": "13873 Main Terrace",
        "city": "Nioro du Rip",
        "country": "Senegal",
        "phone_number": "278-436-1426"
    },
    {
        "user_id": 20,
        "first_name": "Whitman",
        "last_name": "Francescuccio",
        "email": "wfrancescuccioj@google.com.br",
        "gender": "Male",
        "birthdate": "7/21/1962",
        "address": "7333 Portage Terrace",
        "city": "Xinxu",
        "country": "China",
        "phone_number": "871-666-3099"
    },
    {
        "user_id": 21,
        "first_name": "Devora",
        "last_name": "Mitkcov",
        "email": "dmitkcovk@cbslocal.com",
        "gender": "Female",
        "birthdate": "11/22/1983",
        "address": "91656 New Castle Point",
        "city": "Ji’an",
        "country": "China",
        "phone_number": "306-472-9955"
    },
    {
        "user_id": 22,
        "first_name": "Virgie",
        "last_name": "Keble",
        "email": "vkeblel@webmd.com",
        "gender": "Female",
        "birthdate": "12/12/1957",
        "address": "100 Debra Park",
        "city": "Yalkhoy-Mokhk",
        "country": "Russia",
        "phone_number": "560-480-8035"
    },
    {
        "user_id": 23,
        "first_name": "Pearce",
        "last_name": "Stiger",
        "email": "pstigerm@histats.com",
        "gender": "Male",
        "birthdate": "5/21/1956",
        "address": "4 Schlimgen Road",
        "city": "Yezhou",
        "country": "China",
        "phone_number": "765-729-8514"
    },
    {
        "user_id": 24,
        "first_name": "Dalt",
        "last_name": "Rickaert",
        "email": "drickaertn@berkeley.edu",
        "gender": "Male",
        "birthdate": "1/13/1994",
        "address": "3 Fuller Street",
        "city": "Krajan Curahcotok",
        "country": "Indonesia",
        "phone_number": "524-591-9436"
    },
    {
        "user_id": 25,
        "first_name": "Quillan",
        "last_name": "Brimner",
        "email": "qbrimnero@google.cn",
        "gender": "Agender",
        "birthdate": "9/11/1955",
        "address": "78 Onsgard Point",
        "city": "Itsandzéni",
        "country": "Comoros",
        "phone_number": "804-746-6646"
    },
    {
        "user_id": 26,
        "first_name": "Bobine",
        "last_name": "Teresse",
        "email": "bteressep@soup.io",
        "gender": "Female",
        "birthdate": "1/26/1965",
        "address": "9 Ridge Oak Junction",
        "city": "Yamen",
        "country": "China",
        "phone_number": "592-847-4774"
    },
    {
        "user_id": 27,
        "first_name": "Evangeline",
        "last_name": "Bernuzzi",
        "email": "ebernuzziq@webnode.com",
        "gender": "Female",
        "birthdate": "9/18/1986",
        "address": "73449 Hanover Terrace",
        "city": "Prusice",
        "country": "Poland",
        "phone_number": "510-193-0209"
    },
    {
        "user_id": 28,
        "first_name": "Christy",
        "last_name": "Duffrie",
        "email": "cduffrier@cargocollective.com",
        "gender": "Male",
        "birthdate": "7/4/1997",
        "address": "06229 Spohn Plaza",
        "city": "Pangu",
        "country": "China",
        "phone_number": "765-147-7537"
    },
    {
        "user_id": 29,
        "first_name": "Hillery",
        "last_name": "Eake",
        "email": "heakes@va.gov",
        "gender": "Male",
        "birthdate": "6/15/1961",
        "address": "822 North Park",
        "city": "Lufang",
        "country": "China",
        "phone_number": "638-624-0750"
    },
    {
        "user_id": 30,
        "first_name": "Thomas",
        "last_name": "Andrysiak",
        "email": "tandrysiakt@com.com",
        "gender": "Male",
        "birthdate": "9/5/1998",
        "address": "1 Hazelcrest Terrace",
        "city": "Bailu",
        "country": "China",
        "phone_number": "978-860-8403"
    },
    {
        "user_id": 31,
        "first_name": "Towny",
        "last_name": "Heeks",
        "email": "theeksu@facebook.com",
        "gender": "Male",
        "birthdate": "4/14/1978",
        "address": "55755 Monterey Point",
        "city": "Curepipe",
        "country": "Mauritius",
        "phone_number": "253-943-1328"
    },
    {
        "user_id": 32,
        "first_name": "Kenon",
        "last_name": "Menary",
        "email": "kmenaryv@yellowpages.com",
        "gender": "Male",
        "birthdate": "12/17/1965",
        "address": "9 Shasta Center",
        "city": "Alistráti",
        "country": "Greece",
        "phone_number": "158-868-7008"
    },
    {
        "user_id": 33,
        "first_name": "Doug",
        "last_name": "Behning",
        "email": "dbehningw@deliciousdays.com",
        "gender": "Male",
        "birthdate": "5/18/1982",
        "address": "74 Washington Crossing",
        "city": "Patemon",
        "country": "Indonesia",
        "phone_number": "867-357-1167"
    },
    {
        "user_id": 34,
        "first_name": "Ruddie",
        "last_name": "Rooson",
        "email": "rroosonx@usatoday.com",
        "gender": "Male",
        "birthdate": "8/16/1962",
        "address": "8 Washington Park",
        "city": "Bakuriani",
        "country": "Georgia",
        "phone_number": "490-565-4579"
    },
    {
        "user_id": 35,
        "first_name": "Nicolis",
        "last_name": "Bearns",
        "email": "nbearnsy@oracle.com",
        "gender": "Male",
        "birthdate": "2/9/1980",
        "address": "3 Oneill Center",
        "city": "Alençon",
        "country": "France",
        "phone_number": "541-934-4858"
    },
    {
        "user_id": 36,
        "first_name": "Geralda",
        "last_name": "Goodsall",
        "email": "ggoodsallz@ed.gov",
        "gender": "Polygender",
        "birthdate": "5/13/1977",
        "address": "4 Leroy Place",
        "city": "Östersund",
        "country": "Sweden",
        "phone_number": "436-980-3055"
    },
    {
        "user_id": 37,
        "first_name": "Dall",
        "last_name": "Smitten",
        "email": "dsmitten10@tripod.com",
        "gender": "Male",
        "birthdate": "3/11/1986",
        "address": "97 Northfield Road",
        "city": "La Banda",
        "country": "Argentina",
        "phone_number": "808-953-6218"
    },
    {
        "user_id": 38,
        "first_name": "Roselin",
        "last_name": "Bolzen",
        "email": "rbolzen11@list-manage.com",
        "gender": "Female",
        "birthdate": "9/5/1977",
        "address": "618 Walton Hill",
        "city": "Esmeraldas",
        "country": "Ecuador",
        "phone_number": "996-749-5795"
    },
    {
        "user_id": 39,
        "first_name": "Terri",
        "last_name": "Nehl",
        "email": "tnehl12@japanpost.jp",
        "gender": "Female",
        "birthdate": "4/13/1987",
        "address": "78927 Roxbury Avenue",
        "city": "Bungur",
        "country": "Indonesia",
        "phone_number": "412-848-4001"
    },
    {
        "user_id": 40,
        "first_name": "Budd",
        "last_name": "Winckles",
        "email": "bwinckles13@plala.or.jp",
        "gender": "Male",
        "birthdate": "4/5/1961",
        "address": "73 Fairview Drive",
        "city": "Jinquan",
        "country": "China",
        "phone_number": "563-981-4192"
    },
    {
        "user_id": 41,
        "first_name": "Billi",
        "last_name": "Macro",
        "email": "bmacro14@usgs.gov",
        "gender": "Female",
        "birthdate": "8/30/1999",
        "address": "8 Marquette Road",
        "city": "Mont-de-Marsan",
        "country": "France",
        "phone_number": "275-147-1783"
    },
    {
        "user_id": 42,
        "first_name": "Maurie",
        "last_name": "MacCartan",
        "email": "mmaccartan15@skyrock.com",
        "gender": "Male",
        "birthdate": "4/26/1962",
        "address": "810 Rusk Court",
        "city": "Taradale",
        "country": "New Zealand",
        "phone_number": "162-107-0823"
    },
    {
        "user_id": 43,
        "first_name": "Rory",
        "last_name": "Kleanthous",
        "email": "rkleanthous16@walmart.com",
        "gender": "Male",
        "birthdate": "12/17/1968",
        "address": "8 Anthes Hill",
        "city": "Sergeyevka",
        "country": "Russia",
        "phone_number": "986-999-0152"
    },
    {
        "user_id": 44,
        "first_name": "Aggy",
        "last_name": "Libermore",
        "email": "alibermore17@hatena.ne.jp",
        "gender": "Female",
        "birthdate": "8/2/1959",
        "address": "229 Hoard Pass",
        "city": "Carora",
        "country": "Venezuela",
        "phone_number": "757-928-4928"
    },
    {
        "user_id": 45,
        "first_name": "Katleen",
        "last_name": "Castane",
        "email": "kcastane18@bloglovin.com",
        "gender": "Female",
        "birthdate": "7/5/1965",
        "address": "024 Lakewood Plaza",
        "city": "Fort Wayne",
        "country": "United States",
        "phone_number": "260-819-2032"
    },
    {
        "user_id": 46,
        "first_name": "Lazar",
        "last_name": "Bulloch",
        "email": "lbulloch19@usa.gov",
        "gender": "Male",
        "birthdate": "9/4/1962",
        "address": "6 Westend Way",
        "city": "Haukipudas",
        "country": "Finland",
        "phone_number": "345-598-1293"
    },
    {
        "user_id": 47,
        "first_name": "Lishe",
        "last_name": "Kiloh",
        "email": "lkiloh1a@discovery.com",
        "gender": "Female",
        "birthdate": "6/18/1990",
        "address": "595 6th Crossing",
        "city": "Youzai",
        "country": "China",
        "phone_number": "128-483-3259"
    },
    {
        "user_id": 48,
        "first_name": "Aube",
        "last_name": "Bonsul",
        "email": "abonsul1b@google.es",
        "gender": "Male",
        "birthdate": "12/23/1995",
        "address": "33220 Main Way",
        "city": "Yanaoca",
        "country": "Peru",
        "phone_number": "276-947-3505"
    },
    {
        "user_id": 49,
        "first_name": "Franky",
        "last_name": "Yakovich",
        "email": "fyakovich1c@fastcompany.com",
        "gender": "Female",
        "birthdate": "6/5/1952",
        "address": "280 Dryden Lane",
        "city": "Vypolzovo",
        "country": "Russia",
        "phone_number": "753-107-0663"
    },
    {
        "user_id": 50,
        "first_name": "Letisha",
        "last_name": "Griniov",
        "email": "lgriniov1d@prlog.org",
        "gender": "Female",
        "birthdate": "6/8/1993",
        "address": "8588 Luster Drive",
        "city": "Fengshuling",
        "country": "China",
        "phone_number": "171-333-8050"
    },
    {
        "user_id": 51,
        "first_name": "Irena",
        "last_name": "Breeze",
        "email": "ibreeze1e@msu.edu",
        "gender": "Female",
        "birthdate": "11/28/1957",
        "address": "5 Sachs Trail",
        "city": "Telengsari",
        "country": "Indonesia",
        "phone_number": "244-492-6785"
    },
    {
        "user_id": 52,
        "first_name": "Ronny",
        "last_name": "Tennewell",
        "email": "rtennewell1f@shutterfly.com",
        "gender": "Male",
        "birthdate": "3/1/1962",
        "address": "02 Gina Alley",
        "city": "Tân Hiệp",
        "country": "Vietnam",
        "phone_number": "782-626-3099"
    },
    {
        "user_id": 53,
        "first_name": "Katharine",
        "last_name": "Jobling",
        "email": "kjobling1g@opensource.org",
        "gender": "Female",
        "birthdate": "9/13/1983",
        "address": "66010 Anniversary Place",
        "city": "Novo-Peredelkino",
        "country": "Russia",
        "phone_number": "825-730-9581"
    },
    {
        "user_id": 54,
        "first_name": "Gram",
        "last_name": "Dunsire",
        "email": "gdunsire1h@google.es",
        "gender": "Male",
        "birthdate": "12/28/1958",
        "address": "07429 Emmet Road",
        "city": "Qingnianlu",
        "country": "China",
        "phone_number": "851-235-7027"
    },
    {
        "user_id": 55,
        "first_name": "Bat",
        "last_name": "Andrus",
        "email": "bandrus1i@godaddy.com",
        "gender": "Male",
        "birthdate": "10/27/1989",
        "address": "53 Sheridan Court",
        "city": "São Mamede de Infesta",
        "country": "Portugal",
        "phone_number": "365-458-8156"
    },
    {
        "user_id": 56,
        "first_name": "Natividad",
        "last_name": "Gauthorpp",
        "email": "ngauthorpp1j@slideshare.net",
        "gender": "Female",
        "birthdate": "7/6/1979",
        "address": "3 Northridge Junction",
        "city": "Thạnh Hóa",
        "country": "Vietnam",
        "phone_number": "701-119-0861"
    },
    {
        "user_id": 57,
        "first_name": "Eba",
        "last_name": "Thurner",
        "email": "ethurner1k@etsy.com",
        "gender": "Female",
        "birthdate": "8/12/1979",
        "address": "230 Jenna Place",
        "city": "Urechcha",
        "country": "Belarus",
        "phone_number": "318-828-4140"
    },
    {
        "user_id": 58,
        "first_name": "Mollee",
        "last_name": "Aubrey",
        "email": "maubrey1l@yahoo.co.jp",
        "gender": "Female",
        "birthdate": "1/12/1954",
        "address": "839 Anniversary Pass",
        "city": "Mjamaoué",
        "country": "Comoros",
        "phone_number": "954-128-7769"
    },
    {
        "user_id": 59,
        "first_name": "Samantha",
        "last_name": "Poznan",
        "email": "spoznan1m@buzzfeed.com",
        "gender": "Female",
        "birthdate": "12/18/1967",
        "address": "450 Lerdahl Avenue",
        "city": "Oltinko’l",
        "country": "Uzbekistan",
        "phone_number": "856-687-3500"
    },
    {
        "user_id": 60,
        "first_name": "Clemens",
        "last_name": "Towey",
        "email": "ctowey1n@skyrock.com",
        "gender": "Male",
        "birthdate": "4/12/1974",
        "address": "141 Superior Road",
        "city": "Nerokoúros",
        "country": "Greece",
        "phone_number": "245-527-6708"
    },
    {
        "user_id": 61,
        "first_name": "Alphonse",
        "last_name": "Denisovo",
        "email": "adenisovo1o@ca.gov",
        "gender": "Male",
        "birthdate": "2/20/1982",
        "address": "5689 Esker Lane",
        "city": "Soutinho",
        "country": "Portugal",
        "phone_number": "159-770-3635"
    },
    {
        "user_id": 62,
        "first_name": "Hyacinthia",
        "last_name": "Tinmouth",
        "email": "htinmouth1p@nationalgeographic.com",
        "gender": "Polygender",
        "birthdate": "8/4/1982",
        "address": "32419 Northwestern Road",
        "city": "Castañas",
        "country": "Philippines",
        "phone_number": "166-259-4739"
    },
    {
        "user_id": 63,
        "first_name": "Jarvis",
        "last_name": "Arnison",
        "email": "jarnison1q@cnbc.com",
        "gender": "Male",
        "birthdate": "7/22/1950",
        "address": "282 Sycamore Crossing",
        "city": "Tartagal",
        "country": "Argentina",
        "phone_number": "543-687-9919"
    },
    {
        "user_id": 64,
        "first_name": "Malva",
        "last_name": "Bidnall",
        "email": "mbidnall1r@infoseek.co.jp",
        "gender": "Female",
        "birthdate": "10/27/1978",
        "address": "0593 Service Lane",
        "city": "Kissimmee",
        "country": "United States",
        "phone_number": "407-767-0508"
    },
    {
        "user_id": 65,
        "first_name": "Max",
        "last_name": "Fancutt",
        "email": "mfancutt1s@dell.com",
        "gender": "Female",
        "birthdate": "2/10/1989",
        "address": "07 Morningstar Place",
        "city": "Bailu",
        "country": "China",
        "phone_number": "652-355-1669"
    },
    {
        "user_id": 66,
        "first_name": "Conchita",
        "last_name": "Emig",
        "email": "cemig1t@apache.org",
        "gender": "Female",
        "birthdate": "8/25/1990",
        "address": "048 Melrose Terrace",
        "city": "Rangmanten",
        "country": "Indonesia",
        "phone_number": "589-803-1512"
    },
    {
        "user_id": 67,
        "first_name": "Delmer",
        "last_name": "Harriday",
        "email": "dharriday1u@nba.com",
        "gender": "Male",
        "birthdate": "10/16/1976",
        "address": "62 Fair Oaks Plaza",
        "city": "Xin’an",
        "country": "China",
        "phone_number": "125-111-4684"
    },
    {
        "user_id": 68,
        "first_name": "Clarence",
        "last_name": "Largen",
        "email": "clargen1v@cpanel.net",
        "gender": "Male",
        "birthdate": "11/9/1973",
        "address": "74084 Holmberg Pass",
        "city": "Kiraman",
        "country": "Indonesia",
        "phone_number": "948-402-9352"
    },
    {
        "user_id": 69,
        "first_name": "Neill",
        "last_name": "Dubois",
        "email": "ndubois1w@yale.edu",
        "gender": "Male",
        "birthdate": "10/15/1964",
        "address": "6 Straubel Center",
        "city": "Qalqīlyah",
        "country": "Palestinian Territory",
        "phone_number": "385-749-8685"
    },
    {
        "user_id": 70,
        "first_name": "Bucky",
        "last_name": "Morville",
        "email": "bmorville1x@irs.gov",
        "gender": "Male",
        "birthdate": "5/13/1972",
        "address": "90778 Mcguire Street",
        "city": "Ustrzyki Dolne",
        "country": "Poland",
        "phone_number": "255-825-7181"
    },
    {
        "user_id": 71,
        "first_name": "Stella",
        "last_name": "Palke",
        "email": "spalke1y@elpais.com",
        "gender": "Female",
        "birthdate": "7/23/1979",
        "address": "23074 Moulton Junction",
        "city": "Baoshan",
        "country": "China",
        "phone_number": "611-124-8678"
    },
    {
        "user_id": 72,
        "first_name": "Brewer",
        "last_name": "Corkill",
        "email": "bcorkill1z@oakley.com",
        "gender": "Male",
        "birthdate": "9/6/1959",
        "address": "6898 Hoffman Hill",
        "city": "San Jose Village",
        "country": "Northern Mariana Islands",
        "phone_number": "316-491-7338"
    },
    {
        "user_id": 73,
        "first_name": "Abba",
        "last_name": "Allsop",
        "email": "aallsop20@theatlantic.com",
        "gender": "Male",
        "birthdate": "9/4/1964",
        "address": "8125 Mitchell Plaza",
        "city": "Naukšēni",
        "country": "Latvia",
        "phone_number": "217-266-2305"
    },
    {
        "user_id": 74,
        "first_name": "Alphonso",
        "last_name": "Lukacs",
        "email": "alukacs21@noaa.gov",
        "gender": "Non-binary",
        "birthdate": "4/8/1978",
        "address": "3 Dryden Parkway",
        "city": "Novobiryusinskiy",
        "country": "Russia",
        "phone_number": "759-863-8754"
    },
    {
        "user_id": 75,
        "first_name": "Jeremiah",
        "last_name": "Oleksinski",
        "email": "joleksinski22@dyndns.org",
        "gender": "Male",
        "birthdate": "6/23/1954",
        "address": "3051 Moulton Junction",
        "city": "Xintang",
        "country": "China",
        "phone_number": "296-352-4392"
    },
    {
        "user_id": 76,
        "first_name": "Shirlee",
        "last_name": "Barca",
        "email": "sbarca23@lulu.com",
        "gender": "Female",
        "birthdate": "4/7/1965",
        "address": "119 Coleman Pass",
        "city": "Dengjiang",
        "country": "China",
        "phone_number": "862-399-1463"
    },
    {
        "user_id": 77,
        "first_name": "Marris",
        "last_name": "Donson",
        "email": "mdonson24@prweb.com",
        "gender": "Female",
        "birthdate": "12/13/1975",
        "address": "5951 Goodland Park",
        "city": "Sokol",
        "country": "Russia",
        "phone_number": "911-122-3406"
    },
    {
        "user_id": 78,
        "first_name": "Renato",
        "last_name": "Capini",
        "email": "rcapini25@google.ru",
        "gender": "Male",
        "birthdate": "9/10/1968",
        "address": "8 Randy Parkway",
        "city": "Almelo",
        "country": "Netherlands",
        "phone_number": "960-968-7430"
    },
    {
        "user_id": 79,
        "first_name": "Maible",
        "last_name": "Wapples",
        "email": "mwapples26@patch.com",
        "gender": "Genderfluid",
        "birthdate": "3/26/1973",
        "address": "0 Derek Terrace",
        "city": "Badāmā",
        "country": "Syria",
        "phone_number": "681-540-5769"
    },
    {
        "user_id": 80,
        "first_name": "Joseph",
        "last_name": "Melland",
        "email": "jmelland27@xing.com",
        "gender": "Male",
        "birthdate": "6/30/1950",
        "address": "6 Esch Crossing",
        "city": "Donan",
        "country": "Indonesia",
        "phone_number": "471-691-9825"
    },
    {
        "user_id": 81,
        "first_name": "Nil",
        "last_name": "Fencott",
        "email": "nfencott28@woothemes.com",
        "gender": "Male",
        "birthdate": "3/5/1975",
        "address": "94 Oak Valley Point",
        "city": "Kasingan",
        "country": "Indonesia",
        "phone_number": "982-453-5619"
    },
    {
        "user_id": 82,
        "first_name": "Keith",
        "last_name": "Pick",
        "email": "kpick29@nydailynews.com",
        "gender": "Male",
        "birthdate": "1/16/1969",
        "address": "9107 Elmside Junction",
        "city": "Adygeysk",
        "country": "Russia",
        "phone_number": "936-327-0163"
    },
    {
        "user_id": 83,
        "first_name": "Tatiania",
        "last_name": "Baythrop",
        "email": "tbaythrop2a@cmu.edu",
        "gender": "Female",
        "birthdate": "3/22/2002",
        "address": "8954 Sage Road",
        "city": "Wleń",
        "country": "Poland",
        "phone_number": "355-765-3170"
    },
    {
        "user_id": 84,
        "first_name": "Phylis",
        "last_name": "Kindell",
        "email": "pkindell2b@meetup.com",
        "gender": "Female",
        "birthdate": "6/19/1993",
        "address": "99 Lighthouse Bay Parkway",
        "city": "‘Akko",
        "country": "Israel",
        "phone_number": "909-862-9823"
    },
    {
        "user_id": 85,
        "first_name": "Ashly",
        "last_name": "Crocombe",
        "email": "acrocombe2c@ucoz.ru",
        "gender": "Female",
        "birthdate": "11/18/1995",
        "address": "168 Montana Plaza",
        "city": "Khrystynivka",
        "country": "Ukraine",
        "phone_number": "726-328-0475"
    },
    {
        "user_id": 86,
        "first_name": "Shelly",
        "last_name": "Haggar",
        "email": "shaggar2d@ow.ly",
        "gender": "Female",
        "birthdate": "3/7/1965",
        "address": "17763 Harbort Street",
        "city": "Creil",
        "country": "France",
        "phone_number": "535-117-2199"
    },
    {
        "user_id": 87,
        "first_name": "Carroll",
        "last_name": "Dundridge",
        "email": "cdundridge2e@360.cn",
        "gender": "Female",
        "birthdate": "5/17/1986",
        "address": "062 Atwood Plaza",
        "city": "Duofudu",
        "country": "China",
        "phone_number": "635-637-9293"
    },
    {
        "user_id": 88,
        "first_name": "Gothart",
        "last_name": "Farris",
        "email": "gfarris2f@wiley.com",
        "gender": "Male",
        "birthdate": "6/5/1961",
        "address": "1 Thierer Trail",
        "city": "Paranaíba",
        "country": "Brazil",
        "phone_number": "195-149-1973"
    },
    {
        "user_id": 89,
        "first_name": "Dorie",
        "last_name": "De Filippis",
        "email": "ddefilippis2g@g.co",
        "gender": "Genderfluid",
        "birthdate": "7/11/1987",
        "address": "0 Grim Hill",
        "city": "Ogurugu",
        "country": "Nigeria",
        "phone_number": "108-252-0473"
    },
    {
        "user_id": 90,
        "first_name": "Georg",
        "last_name": "Motte",
        "email": "gmotte2h@dailymotion.com",
        "gender": "Male",
        "birthdate": "6/24/1954",
        "address": "36 Corry Avenue",
        "city": "Mocímboa",
        "country": "Mozambique",
        "phone_number": "327-793-5270"
    },
    {
        "user_id": 91,
        "first_name": "Georgena",
        "last_name": "Antonietti",
        "email": "gantonietti2i@gmpg.org",
        "gender": "Female",
        "birthdate": "1/2/1952",
        "address": "8 Hoepker Crossing",
        "city": "San Cristobal",
        "country": "Mexico",
        "phone_number": "359-706-2977"
    },
    {
        "user_id": 92,
        "first_name": "Granger",
        "last_name": "Glanister",
        "email": "gglanister2j@vk.com",
        "gender": "Male",
        "birthdate": "11/10/1985",
        "address": "6013 Hagan Street",
        "city": "Reutov",
        "country": "Russia",
        "phone_number": "248-338-2771"
    },
    {
        "user_id": 93,
        "first_name": "Isa",
        "last_name": "Frudd",
        "email": "ifrudd2k@themeforest.net",
        "gender": "Male",
        "birthdate": "3/28/1967",
        "address": "6283 Green Place",
        "city": "Suhopolje",
        "country": "Croatia",
        "phone_number": "778-307-3719"
    },
    {
        "user_id": 94,
        "first_name": "Alla",
        "last_name": "Bertelmot",
        "email": "abertelmot2l@zimbio.com",
        "gender": "Female",
        "birthdate": "5/12/1979",
        "address": "6 Magdeline Terrace",
        "city": "Madjeouéni",
        "country": "Comoros",
        "phone_number": "329-287-2359"
    },
    {
        "user_id": 95,
        "first_name": "Darin",
        "last_name": "Kachel",
        "email": "dkachel2m@wisc.edu",
        "gender": "Male",
        "birthdate": "12/1/1999",
        "address": "46257 Oneill Plaza",
        "city": "Barrancas",
        "country": "Colombia",
        "phone_number": "122-224-8781"
    },
    {
        "user_id": 96,
        "first_name": "Terrence",
        "last_name": "Rewcassell",
        "email": "trewcassell2n@ehow.com",
        "gender": "Male",
        "birthdate": "3/30/1993",
        "address": "56083 Mccormick Road",
        "city": "Djibouti",
        "country": "Djibouti",
        "phone_number": "986-702-9561"
    },
    {
        "user_id": 97,
        "first_name": "Lexine",
        "last_name": "Linnard",
        "email": "llinnard2o@ycombinator.com",
        "gender": "Female",
        "birthdate": "4/21/1952",
        "address": "84405 Park Meadow Circle",
        "city": "Pita Kotte",
        "country": "Sri Lanka",
        "phone_number": "316-245-1440"
    },
    {
        "user_id": 98,
        "first_name": "Ryan",
        "last_name": "Wyatt",
        "email": "rwyatt2p@spotify.com",
        "gender": "Male",
        "birthdate": "12/10/1961",
        "address": "8253 Hoepker Point",
        "city": "Varberg",
        "country": "Sweden",
        "phone_number": "726-644-1233"
    },
    {
        "user_id": 99,
        "first_name": "Donnie",
        "last_name": "Dalling",
        "email": "ddalling2q@last.fm",
        "gender": "Male",
        "birthdate": "8/11/1981",
        "address": "4108 Kim Road",
        "city": "Mocupe",
        "country": "Peru",
        "phone_number": "262-673-6694"
    },
    {
        "user_id": 100,
        "first_name": "Kalil",
        "last_name": "Atwell",
        "email": "katwell2r@wp.com",
        "gender": "Male",
        "birthdate": "6/15/1956",
        "address": "54 Dottie Way",
        "city": "Hesheng",
        "country": "China",
        "phone_number": "596-260-2477"
    },
    {
        "user_id": 101,
        "first_name": "Norbie",
        "last_name": "Gozzett",
        "email": "ngozzett2s@sourceforge.net",
        "gender": "Male",
        "birthdate": "3/25/1987",
        "address": "47269 Bluestem Court",
        "city": "Mendes",
        "country": "Brazil",
        "phone_number": "357-417-4625"
    },
    {
        "user_id": 102,
        "first_name": "Xaviera",
        "last_name": "Singyard",
        "email": "xsingyard2t@hud.gov",
        "gender": "Non-binary",
        "birthdate": "1/25/1973",
        "address": "08255 Canary Way",
        "city": "Xiawuqi",
        "country": "China",
        "phone_number": "838-452-1144"
    },
    {
        "user_id": 103,
        "first_name": "Darcy",
        "last_name": "Polfer",
        "email": "dpolfer2u@tiny.cc",
        "gender": "Male",
        "birthdate": "3/4/1977",
        "address": "89211 Warner Crossing",
        "city": "Teseney",
        "country": "Eritrea",
        "phone_number": "191-390-2408"
    },
    {
        "user_id": 104,
        "first_name": "Piggy",
        "last_name": "Danett",
        "email": "pdanett2v@clickbank.net",
        "gender": "Male",
        "birthdate": "9/28/1992",
        "address": "860 Thackeray Park",
        "city": "Tobruk",
        "country": "Libya",
        "phone_number": "470-393-3270"
    },
    {
        "user_id": 105,
        "first_name": "Pip",
        "last_name": "Habben",
        "email": "phabben2w@webs.com",
        "gender": "Male",
        "birthdate": "5/12/1992",
        "address": "6 Oneill Road",
        "city": "Chikwawa",
        "country": "Malawi",
        "phone_number": "714-268-6989"
    },
    {
        "user_id": 106,
        "first_name": "Jesse",
        "last_name": "Massei",
        "email": "jmassei2x@alexa.com",
        "gender": "Male",
        "birthdate": "6/2/1998",
        "address": "2 Tony Park",
        "city": "Azogues",
        "country": "Ecuador",
        "phone_number": "352-241-0121"
    },
    {
        "user_id": 107,
        "first_name": "Dorene",
        "last_name": "Lashford",
        "email": "dlashford2y@webs.com",
        "gender": "Female",
        "birthdate": "8/28/1964",
        "address": "7005 2nd Drive",
        "city": "Parse",
        "country": "Indonesia",
        "phone_number": "383-132-7960"
    },
    {
        "user_id": 108,
        "first_name": "Chastity",
        "last_name": "Dobkin",
        "email": "cdobkin2z@archive.org",
        "gender": "Female",
        "birthdate": "4/28/1995",
        "address": "8 Mesta Hill",
        "city": "Ústí nad Labem",
        "country": "Czech Republic",
        "phone_number": "337-100-6309"
    },
    {
        "user_id": 109,
        "first_name": "Bruce",
        "last_name": "Romero",
        "email": "bromero30@freewebs.com",
        "gender": "Male",
        "birthdate": "10/15/1975",
        "address": "62 Monterey Crossing",
        "city": "Pierzchnica",
        "country": "Poland",
        "phone_number": "965-635-0790"
    },
    {
        "user_id": 110,
        "first_name": "Pearla",
        "last_name": "Steggles",
        "email": "psteggles31@indiatimes.com",
        "gender": "Female",
        "birthdate": "1/26/1969",
        "address": "46 Schurz Lane",
        "city": "San Enrique",
        "country": "Philippines",
        "phone_number": "273-896-6060"
    },
    {
        "user_id": 111,
        "first_name": "Danny",
        "last_name": "Aughton",
        "email": "daughton32@amazon.co.jp",
        "gender": "Male",
        "birthdate": "12/3/1985",
        "address": "72846 Westend Avenue",
        "city": "Néa Pélla",
        "country": "Greece",
        "phone_number": "348-318-3330"
    },
    {
        "user_id": 112,
        "first_name": "Skipp",
        "last_name": "Barwick",
        "email": "sbarwick33@wp.com",
        "gender": "Male",
        "birthdate": "3/14/1999",
        "address": "73 Warbler Center",
        "city": "Fundación",
        "country": "Colombia",
        "phone_number": "641-773-3538"
    },
    {
        "user_id": 113,
        "first_name": "Catarina",
        "last_name": "Chettle",
        "email": "cchettle34@msn.com",
        "gender": "Female",
        "birthdate": "1/8/1999",
        "address": "8 Caliangt Trail",
        "city": "Cambuí",
        "country": "Brazil",
        "phone_number": "501-997-6531"
    },
    {
        "user_id": 114,
        "first_name": "Kahaleel",
        "last_name": "Pargiter",
        "email": "kpargiter35@gmpg.org",
        "gender": "Male",
        "birthdate": "11/27/1972",
        "address": "2406 Tony Street",
        "city": "Arlington",
        "country": "United States",
        "phone_number": "571-516-8900"
    },
    {
        "user_id": 115,
        "first_name": "Melina",
        "last_name": "Sirmon",
        "email": "msirmon36@about.me",
        "gender": "Female",
        "birthdate": "3/22/1985",
        "address": "164 Ohio Crossing",
        "city": "Mujães",
        "country": "Portugal",
        "phone_number": "140-702-8931"
    },
    {
        "user_id": 116,
        "first_name": "Bel",
        "last_name": "Loraine",
        "email": "bloraine37@github.com",
        "gender": "Female",
        "birthdate": "2/9/2002",
        "address": "2128 Eliot Center",
        "city": "Barajevo",
        "country": "Serbia",
        "phone_number": "127-440-9656"
    },
    {
        "user_id": 117,
        "first_name": "Conrade",
        "last_name": "Troni",
        "email": "ctroni38@lulu.com",
        "gender": "Male",
        "birthdate": "9/25/1979",
        "address": "86142 Blue Bill Park Drive",
        "city": "Ballyhaunis",
        "country": "Ireland",
        "phone_number": "322-386-2652"
    },
    {
        "user_id": 118,
        "first_name": "Giovanni",
        "last_name": "Capitano",
        "email": "gcapitano39@princeton.edu",
        "gender": "Male",
        "birthdate": "9/23/1996",
        "address": "0440 Loftsgordon Street",
        "city": "Sa'dah",
        "country": "Yemen",
        "phone_number": "246-804-1702"
    },
    {
        "user_id": 119,
        "first_name": "Caty",
        "last_name": "Orcas",
        "email": "corcas3a@theglobeandmail.com",
        "gender": "Female",
        "birthdate": "8/20/1985",
        "address": "2657 Kensington Circle",
        "city": "Lashio",
        "country": "Myanmar",
        "phone_number": "506-537-6223"
    },
    {
        "user_id": 120,
        "first_name": "Nikolai",
        "last_name": "Sibun",
        "email": "nsibun3b@etsy.com",
        "gender": "Male",
        "birthdate": "1/23/1954",
        "address": "84176 Superior Alley",
        "city": "Åkersberga",
        "country": "Sweden",
        "phone_number": "589-603-6801"
    },
    {
        "user_id": 121,
        "first_name": "Emerson",
        "last_name": "Kilmurray",
        "email": "ekilmurray3c@mozilla.org",
        "gender": "Genderqueer",
        "birthdate": "6/15/1967",
        "address": "63648 Memorial Drive",
        "city": "Níkiti",
        "country": "Greece",
        "phone_number": "435-981-8022"
    },
    {
        "user_id": 122,
        "first_name": "Tyler",
        "last_name": "Haughin",
        "email": "thaughin3d@amazonaws.com",
        "gender": "Male",
        "birthdate": "6/10/1990",
        "address": "3468 Forest Center",
        "city": "Olszówka",
        "country": "Poland",
        "phone_number": "485-663-6501"
    },
    {
        "user_id": 123,
        "first_name": "Mattias",
        "last_name": "Ossipenko",
        "email": "mossipenko3e@cam.ac.uk",
        "gender": "Male",
        "birthdate": "9/10/1971",
        "address": "8 Eagan Court",
        "city": "Samayac",
        "country": "Guatemala",
        "phone_number": "719-584-3912"
    },
    {
        "user_id": 124,
        "first_name": "Haven",
        "last_name": "Lamplugh",
        "email": "hlamplugh3f@theglobeandmail.com",
        "gender": "Male",
        "birthdate": "8/31/1978",
        "address": "15 Old Shore Drive",
        "city": "Terong",
        "country": "Indonesia",
        "phone_number": "228-990-8319"
    },
    {
        "user_id": 125,
        "first_name": "Sherry",
        "last_name": "Stowe",
        "email": "sstowe3g@wired.com",
        "gender": "Female",
        "birthdate": "6/9/1959",
        "address": "6154 Waubesa Junction",
        "city": "Shah Alam",
        "country": "Malaysia",
        "phone_number": "252-722-1138"
    },
    {
        "user_id": 126,
        "first_name": "Sonja",
        "last_name": "Inglis",
        "email": "singlis3h@hatena.ne.jp",
        "gender": "Female",
        "birthdate": "1/17/1970",
        "address": "4 5th Lane",
        "city": "Bry-sur-Marne",
        "country": "France",
        "phone_number": "275-860-5342"
    },
    {
        "user_id": 127,
        "first_name": "Anallese",
        "last_name": "Huckerbe",
        "email": "ahuckerbe3i@goodreads.com",
        "gender": "Female",
        "birthdate": "3/17/1997",
        "address": "652 Florence Lane",
        "city": "Uppsala",
        "country": "Sweden",
        "phone_number": "181-130-5966"
    },
    {
        "user_id": 128,
        "first_name": "Anthea",
        "last_name": "MacAlinden",
        "email": "amacalinden3j@berkeley.edu",
        "gender": "Female",
        "birthdate": "6/27/1967",
        "address": "006 Del Mar Street",
        "city": "Sasar",
        "country": "Indonesia",
        "phone_number": "291-369-8479"
    },
    {
        "user_id": 129,
        "first_name": "Leta",
        "last_name": "Gorsse",
        "email": "lgorsse3k@homestead.com",
        "gender": "Female",
        "birthdate": "12/9/1959",
        "address": "5196 Hauk Road",
        "city": "Yihe",
        "country": "China",
        "phone_number": "368-100-8176"
    },
    {
        "user_id": 130,
        "first_name": "Nolana",
        "last_name": "Juniper",
        "email": "njuniper3l@loc.gov",
        "gender": "Female",
        "birthdate": "8/31/1995",
        "address": "8753 Blaine Avenue",
        "city": "Murom",
        "country": "Russia",
        "phone_number": "927-827-2827"
    },
    {
        "user_id": 131,
        "first_name": "Moritz",
        "last_name": "Antonin",
        "email": "mantonin3m@jiathis.com",
        "gender": "Male",
        "birthdate": "8/9/1968",
        "address": "08 Corry Lane",
        "city": "Tarikolot",
        "country": "Indonesia",
        "phone_number": "742-111-0639"
    },
    {
        "user_id": 132,
        "first_name": "Jelene",
        "last_name": "Dykas",
        "email": "jdykas3n@lycos.com",
        "gender": "Female",
        "birthdate": "3/16/1960",
        "address": "441 Di Loreto Plaza",
        "city": "Ciriri",
        "country": "Indonesia",
        "phone_number": "541-227-9273"
    },
    {
        "user_id": 133,
        "first_name": "Jammie",
        "last_name": "Goldby",
        "email": "jgoldby3o@reuters.com",
        "gender": "Female",
        "birthdate": "12/7/1981",
        "address": "35993 Summerview Trail",
        "city": "Guri-si",
        "country": "South Korea",
        "phone_number": "718-693-5470"
    },
    {
        "user_id": 134,
        "first_name": "Hyacinth",
        "last_name": "Henrych",
        "email": "hhenrych3p@alexa.com",
        "gender": "Female",
        "birthdate": "1/26/1974",
        "address": "4 Beilfuss Way",
        "city": "Luče",
        "country": "Slovenia",
        "phone_number": "250-746-2649"
    },
    {
        "user_id": 135,
        "first_name": "Mia",
        "last_name": "Balnaves",
        "email": "mbalnaves3q@comcast.net",
        "gender": "Female",
        "birthdate": "2/5/1988",
        "address": "809 Nova Court",
        "city": "Paucarbamba",
        "country": "Peru",
        "phone_number": "434-685-1026"
    },
    {
        "user_id": 136,
        "first_name": "Gavan",
        "last_name": "Stevens",
        "email": "gstevens3r@timesonline.co.uk",
        "gender": "Male",
        "birthdate": "5/17/2001",
        "address": "0 Duke Lane",
        "city": "Aguas Verdes",
        "country": "Peru",
        "phone_number": "922-566-7163"
    },
    {
        "user_id": 137,
        "first_name": "Gerry",
        "last_name": "Smewings",
        "email": "gsmewings3s@moonfruit.com",
        "gender": "Female",
        "birthdate": "10/5/1993",
        "address": "9760 Scott Plaza",
        "city": "Mondragon",
        "country": "Philippines",
        "phone_number": "184-661-7098"
    },
    {
        "user_id": 138,
        "first_name": "Chen",
        "last_name": "Calcut",
        "email": "ccalcut3t@sphinn.com",
        "gender": "Male",
        "birthdate": "3/9/1954",
        "address": "35 Continental Court",
        "city": "Longbei",
        "country": "China",
        "phone_number": "767-843-0832"
    },
    {
        "user_id": 139,
        "first_name": "Javier",
        "last_name": "Casarino",
        "email": "jcasarino3u@oaic.gov.au",
        "gender": "Male",
        "birthdate": "1/4/1999",
        "address": "3250 Blue Bill Park Lane",
        "city": "Al Metlaoui",
        "country": "Tunisia",
        "phone_number": "802-929-2185"
    },
    {
        "user_id": 140,
        "first_name": "Dody",
        "last_name": "Franzotto",
        "email": "dfranzotto3v@chronoengine.com",
        "gender": "Female",
        "birthdate": "6/7/1988",
        "address": "8 Badeau Road",
        "city": "Banjar Banyualit",
        "country": "Indonesia",
        "phone_number": "657-867-4907"
    },
    {
        "user_id": 141,
        "first_name": "Cleavland",
        "last_name": "Whitham",
        "email": "cwhitham3w@com.com",
        "gender": "Male",
        "birthdate": "5/21/1998",
        "address": "5076 Dayton Avenue",
        "city": "Roshal’",
        "country": "Russia",
        "phone_number": "600-348-0289"
    },
    {
        "user_id": 142,
        "first_name": "Herbie",
        "last_name": "Caseri",
        "email": "hcaseri3x@nyu.edu",
        "gender": "Genderqueer",
        "birthdate": "7/12/1977",
        "address": "8390 Hollow Ridge Place",
        "city": "Václavovice",
        "country": "Czech Republic",
        "phone_number": "959-705-5534"
    },
    {
        "user_id": 143,
        "first_name": "Sonny",
        "last_name": "Vondruska",
        "email": "svondruska3y@dmoz.org",
        "gender": "Female",
        "birthdate": "11/27/1996",
        "address": "461 Rowland Park",
        "city": "Purwokerto",
        "country": "Indonesia",
        "phone_number": "325-368-5388"
    },
    {
        "user_id": 144,
        "first_name": "Keriann",
        "last_name": "Gatiss",
        "email": "kgatiss3z@nymag.com",
        "gender": "Female",
        "birthdate": "3/25/1974",
        "address": "567 Hanover Lane",
        "city": "Xipingle",
        "country": "China",
        "phone_number": "946-318-2458"
    },
    {
        "user_id": 145,
        "first_name": "Kirstin",
        "last_name": "McFfaden",
        "email": "kmcffaden40@squidoo.com",
        "gender": "Female",
        "birthdate": "8/27/1951",
        "address": "8411 Johnson Point",
        "city": "Dagohoy",
        "country": "Philippines",
        "phone_number": "638-856-6019"
    },
    {
        "user_id": 146,
        "first_name": "Marleen",
        "last_name": "Gookey",
        "email": "mgookey41@pinterest.com",
        "gender": "Female",
        "birthdate": "8/16/1993",
        "address": "429 Annamark Alley",
        "city": "Łobez",
        "country": "Poland",
        "phone_number": "918-657-3913"
    },
    {
        "user_id": 147,
        "first_name": "Jonas",
        "last_name": "Read",
        "email": "jread42@google.co.jp",
        "gender": "Male",
        "birthdate": "6/4/2001",
        "address": "70 Judy Avenue",
        "city": "Dalamdesa Kalapadua",
        "country": "Indonesia",
        "phone_number": "983-486-7123"
    },
    {
        "user_id": 148,
        "first_name": "Tore",
        "last_name": "Konke",
        "email": "tkonke43@yale.edu",
        "gender": "Male",
        "birthdate": "5/21/1982",
        "address": "43518 Stone Corner Hill",
        "city": "Astorga",
        "country": "Brazil",
        "phone_number": "521-831-4670"
    },
    {
        "user_id": 149,
        "first_name": "Virgie",
        "last_name": "Szapiro",
        "email": "vszapiro44@constantcontact.com",
        "gender": "Male",
        "birthdate": "11/28/1970",
        "address": "25 Independence Trail",
        "city": "Gagarin",
        "country": "Uzbekistan",
        "phone_number": "854-325-5814"
    },
    {
        "user_id": 150,
        "first_name": "Fionna",
        "last_name": "Welbrock",
        "email": "fwelbrock45@facebook.com",
        "gender": "Female",
        "birthdate": "11/15/1964",
        "address": "06656 Superior Crossing",
        "city": "Rybnik",
        "country": "Poland",
        "phone_number": "282-217-6050"
    },
    {
        "user_id": 151,
        "first_name": "Boycie",
        "last_name": "Hearse",
        "email": "bhearse46@spiegel.de",
        "gender": "Male",
        "birthdate": "8/21/1991",
        "address": "70047 Logan Road",
        "city": "Gelsenkirchen",
        "country": "Germany",
        "phone_number": "967-282-5703"
    },
    {
        "user_id": 152,
        "first_name": "Matilda",
        "last_name": "Gladdish",
        "email": "mgladdish47@tamu.edu",
        "gender": "Female",
        "birthdate": "7/4/1975",
        "address": "81 Ridgeview Hill",
        "city": "Mabilog",
        "country": "Philippines",
        "phone_number": "859-669-6560"
    },
    {
        "user_id": 153,
        "first_name": "Olivia",
        "last_name": "Switsur",
        "email": "oswitsur48@163.com",
        "gender": "Female",
        "birthdate": "12/21/1952",
        "address": "0 Mayer Court",
        "city": "Yolöten",
        "country": "Turkmenistan",
        "phone_number": "347-526-7088"
    },
    {
        "user_id": 154,
        "first_name": "Ezequiel",
        "last_name": "Kitlee",
        "email": "ekitlee49@mayoclinic.com",
        "gender": "Male",
        "birthdate": "10/30/1994",
        "address": "2 Glendale Lane",
        "city": "Jinji",
        "country": "China",
        "phone_number": "902-938-0447"
    },
    {
        "user_id": 155,
        "first_name": "Tawnya",
        "last_name": "Pidwell",
        "email": "tpidwell4a@vimeo.com",
        "gender": "Female",
        "birthdate": "8/4/1957",
        "address": "7415 Meadow Ridge Park",
        "city": "Al Munīrah",
        "country": "Yemen",
        "phone_number": "643-636-1366"
    },
    {
        "user_id": 156,
        "first_name": "Corri",
        "last_name": "von Hagt",
        "email": "cvonhagt4b@engadget.com",
        "gender": "Female",
        "birthdate": "5/12/1971",
        "address": "56069 Corben Place",
        "city": "Nīca",
        "country": "Latvia",
        "phone_number": "396-554-2626"
    },
    {
        "user_id": 157,
        "first_name": "Darla",
        "last_name": "De Ferrari",
        "email": "ddeferrari4c@tiny.cc",
        "gender": "Non-binary",
        "birthdate": "7/2/1953",
        "address": "61551 Emmet Point",
        "city": "Sakata",
        "country": "Japan",
        "phone_number": "140-580-9187"
    },
    {
        "user_id": 158,
        "first_name": "Godiva",
        "last_name": "Sein",
        "email": "gsein4d@time.com",
        "gender": "Female",
        "birthdate": "1/31/1973",
        "address": "24138 Rowland Terrace",
        "city": "Samphanthawong",
        "country": "Thailand",
        "phone_number": "234-284-7156"
    },
    {
        "user_id": 159,
        "first_name": "Cecilio",
        "last_name": "Sandbatch",
        "email": "csandbatch4e@jugem.jp",
        "gender": "Male",
        "birthdate": "11/4/1995",
        "address": "73 Rusk Avenue",
        "city": "Orléans",
        "country": "France",
        "phone_number": "870-245-3857"
    },
    {
        "user_id": 160,
        "first_name": "Beverlie",
        "last_name": "Coolbear",
        "email": "bcoolbear4f@studiopress.com",
        "gender": "Female",
        "birthdate": "2/10/1951",
        "address": "93 Hagan Trail",
        "city": "Mesa",
        "country": "United States",
        "phone_number": "480-954-5511"
    },
    {
        "user_id": 161,
        "first_name": "Darcy",
        "last_name": "Jeffries",
        "email": "djeffries4g@ebay.co.uk",
        "gender": "Male",
        "birthdate": "7/1/1961",
        "address": "62697 Kropf Avenue",
        "city": "Baroh",
        "country": "Indonesia",
        "phone_number": "918-577-4147"
    },
    {
        "user_id": 162,
        "first_name": "Harmonie",
        "last_name": "Chevolleau",
        "email": "hchevolleau4h@multiply.com",
        "gender": "Bigender",
        "birthdate": "3/25/1987",
        "address": "6671 Eastwood Road",
        "city": "Nicolas Bravo",
        "country": "Mexico",
        "phone_number": "384-948-4754"
    },
    {
        "user_id": 163,
        "first_name": "Dalia",
        "last_name": "Shalders",
        "email": "dshalders4i@washingtonpost.com",
        "gender": "Female",
        "birthdate": "3/19/1950",
        "address": "8783 Sutherland Pass",
        "city": "Agdangan",
        "country": "Philippines",
        "phone_number": "660-125-0905"
    },
    {
        "user_id": 164,
        "first_name": "Aguste",
        "last_name": "Humberston",
        "email": "ahumberston4j@com.com",
        "gender": "Male",
        "birthdate": "12/8/1957",
        "address": "60 Scofield Circle",
        "city": "Liboran",
        "country": "Philippines",
        "phone_number": "521-466-9777"
    },
    {
        "user_id": 165,
        "first_name": "Mindy",
        "last_name": "Bleythin",
        "email": "mbleythin4k@hubpages.com",
        "gender": "Female",
        "birthdate": "6/13/1992",
        "address": "07 Bunting Center",
        "city": "Yangon",
        "country": "Myanmar",
        "phone_number": "603-395-6965"
    },
    {
        "user_id": 166,
        "first_name": "Malvin",
        "last_name": "Klaffs",
        "email": "mklaffs4l@hp.com",
        "gender": "Male",
        "birthdate": "9/24/1956",
        "address": "8467 Thackeray Way",
        "city": "Calhetas",
        "country": "Portugal",
        "phone_number": "309-876-6580"
    },
    {
        "user_id": 167,
        "first_name": "Alix",
        "last_name": "Wands",
        "email": "awands4m@businesswire.com",
        "gender": "Male",
        "birthdate": "8/11/1988",
        "address": "10 Goodland Road",
        "city": "Siqian",
        "country": "China",
        "phone_number": "473-369-2099"
    },
    {
        "user_id": 168,
        "first_name": "Juana",
        "last_name": "Twell",
        "email": "jtwell4n@last.fm",
        "gender": "Female",
        "birthdate": "8/4/1963",
        "address": "2386 Bowman Pass",
        "city": "Kotaagung",
        "country": "Indonesia",
        "phone_number": "175-688-2552"
    },
    {
        "user_id": 169,
        "first_name": "Jamill",
        "last_name": "Evins",
        "email": "jevins4o@pagesperso-orange.fr",
        "gender": "Polygender",
        "birthdate": "3/2/1996",
        "address": "552 Bowman Plaza",
        "city": "Xixiang",
        "country": "China",
        "phone_number": "783-823-1673"
    },
    {
        "user_id": 170,
        "first_name": "Clare",
        "last_name": "Hendrix",
        "email": "chendrix4p@123-reg.co.uk",
        "gender": "Male",
        "birthdate": "3/14/1989",
        "address": "97276 Meadow Ridge Circle",
        "city": "Ash Shawātī",
        "country": "Yemen",
        "phone_number": "150-599-2871"
    },
    {
        "user_id": 171,
        "first_name": "Boigie",
        "last_name": "Wands",
        "email": "bwands4q@mozilla.com",
        "gender": "Male",
        "birthdate": "11/10/1955",
        "address": "6 Kensington Avenue",
        "city": "Muquiyauyo",
        "country": "Peru",
        "phone_number": "789-700-1828"
    },
    {
        "user_id": 172,
        "first_name": "Asa",
        "last_name": "Checcuzzi",
        "email": "acheccuzzi4r@jalbum.net",
        "gender": "Male",
        "birthdate": "2/18/1992",
        "address": "74 Springview Street",
        "city": "Lille",
        "country": "France",
        "phone_number": "934-463-6486"
    },
    {
        "user_id": 173,
        "first_name": "Sue",
        "last_name": "Courson",
        "email": "scourson4s@guardian.co.uk",
        "gender": "Female",
        "birthdate": "9/13/1961",
        "address": "33 Myrtle Point",
        "city": "Riachão do Jacuípe",
        "country": "Brazil",
        "phone_number": "496-443-7792"
    },
    {
        "user_id": 174,
        "first_name": "Enriqueta",
        "last_name": "Muddiman",
        "email": "emuddiman4t@columbia.edu",
        "gender": "Female",
        "birthdate": "7/1/1962",
        "address": "52 Packers Crossing",
        "city": "Pak Phanang",
        "country": "Thailand",
        "phone_number": "333-295-4246"
    },
    {
        "user_id": 175,
        "first_name": "Jaclyn",
        "last_name": "Lamplugh",
        "email": "jlamplugh4u@phoca.cz",
        "gender": "Female",
        "birthdate": "11/23/1987",
        "address": "820 Morrow Circle",
        "city": "Bol’shoy Kamen’",
        "country": "Russia",
        "phone_number": "539-287-7734"
    },
    {
        "user_id": 176,
        "first_name": "Roxi",
        "last_name": "Hanselmann",
        "email": "rhanselmann4v@about.me",
        "gender": "Female",
        "birthdate": "12/26/1989",
        "address": "6 Briar Crest Park",
        "city": "Markham",
        "country": "Canada",
        "phone_number": "427-626-1445"
    },
    {
        "user_id": 177,
        "first_name": "Zachariah",
        "last_name": "Stirzaker",
        "email": "zstirzaker4w@stanford.edu",
        "gender": "Male",
        "birthdate": "4/6/1974",
        "address": "042 Banding Avenue",
        "city": "San Francisco",
        "country": "United States",
        "phone_number": "415-516-9379"
    },
    {
        "user_id": 178,
        "first_name": "Dianemarie",
        "last_name": "Jandak",
        "email": "djandak4x@mac.com",
        "gender": "Female",
        "birthdate": "5/4/1982",
        "address": "0376 Ronald Regan Park",
        "city": "Naha-shi",
        "country": "Japan",
        "phone_number": "807-221-7253"
    },
    {
        "user_id": 179,
        "first_name": "Carlie",
        "last_name": "Otson",
        "email": "cotson4y@sourceforge.net",
        "gender": "Male",
        "birthdate": "4/2/2000",
        "address": "852 Ridge Oak Park",
        "city": "Limeira",
        "country": "Brazil",
        "phone_number": "571-805-0844"
    },
    {
        "user_id": 180,
        "first_name": "Whittaker",
        "last_name": "Imm",
        "email": "wimm4z@cbsnews.com",
        "gender": "Male",
        "birthdate": "4/26/1965",
        "address": "17 Kinsman Alley",
        "city": "Grenoble",
        "country": "France",
        "phone_number": "769-866-4902"
    },
    {
        "user_id": 181,
        "first_name": "Rosella",
        "last_name": "Embra",
        "email": "rembra50@posterous.com",
        "gender": "Female",
        "birthdate": "2/18/1978",
        "address": "15613 Vahlen Pass",
        "city": "Qo‘qon",
        "country": "Uzbekistan",
        "phone_number": "632-176-2416"
    },
    {
        "user_id": 182,
        "first_name": "Tony",
        "last_name": "Lodden",
        "email": "tlodden51@hugedomains.com",
        "gender": "Female",
        "birthdate": "4/27/1956",
        "address": "552 Lindbergh Center",
        "city": "Nyahururu",
        "country": "Kenya",
        "phone_number": "109-983-6502"
    },
    {
        "user_id": 183,
        "first_name": "Augustus",
        "last_name": "Ick",
        "email": "aick52@hatena.ne.jp",
        "gender": "Male",
        "birthdate": "2/11/1972",
        "address": "95 Cardinal Point",
        "city": "Urzuf",
        "country": "Ukraine",
        "phone_number": "999-737-9512"
    },
    {
        "user_id": 184,
        "first_name": "Dimitri",
        "last_name": "Bourgour",
        "email": "dbourgour53@ycombinator.com",
        "gender": "Agender",
        "birthdate": "10/28/1999",
        "address": "628 Lerdahl Street",
        "city": "Göteborg",
        "country": "Sweden",
        "phone_number": "741-858-9699"
    },
    {
        "user_id": 185,
        "first_name": "Cordy",
        "last_name": "Emms",
        "email": "cemms54@blinklist.com",
        "gender": "Male",
        "birthdate": "6/25/1986",
        "address": "58214 Jana Terrace",
        "city": "Zinat",
        "country": "Morocco",
        "phone_number": "127-564-3395"
    },
    {
        "user_id": 186,
        "first_name": "Georgeta",
        "last_name": "Bobasch",
        "email": "gbobasch55@weebly.com",
        "gender": "Genderqueer",
        "birthdate": "10/12/1993",
        "address": "6203 La Follette Place",
        "city": "Muara",
        "country": "Indonesia",
        "phone_number": "361-668-1247"
    },
    {
        "user_id": 187,
        "first_name": "Eirena",
        "last_name": "Kenefick",
        "email": "ekenefick56@miibeian.gov.cn",
        "gender": "Female",
        "birthdate": "3/1/1972",
        "address": "0 Bobwhite Crossing",
        "city": "Nanggewer",
        "country": "Indonesia",
        "phone_number": "748-336-2380"
    },
    {
        "user_id": 188,
        "first_name": "York",
        "last_name": "Cregin",
        "email": "ycregin57@oakley.com",
        "gender": "Male",
        "birthdate": "3/4/1967",
        "address": "8962 Fulton Circle",
        "city": "Queimados",
        "country": "Brazil",
        "phone_number": "358-133-4014"
    },
    {
        "user_id": 189,
        "first_name": "Tybalt",
        "last_name": "Yakovlev",
        "email": "tyakovlev58@ft.com",
        "gender": "Male",
        "birthdate": "6/25/2002",
        "address": "5 Kenwood Drive",
        "city": "Kato Pyrgos",
        "country": "Cyprus",
        "phone_number": "813-564-0330"
    },
    {
        "user_id": 190,
        "first_name": "Corina",
        "last_name": "Cowitz",
        "email": "ccowitz59@cdbaby.com",
        "gender": "Female",
        "birthdate": "6/24/1985",
        "address": "563 Golden Leaf Center",
        "city": "Terezín",
        "country": "Czech Republic",
        "phone_number": "369-449-5118"
    },
    {
        "user_id": 191,
        "first_name": "Urbain",
        "last_name": "Royl",
        "email": "uroyl5a@economist.com",
        "gender": "Male",
        "birthdate": "6/14/1980",
        "address": "68813 International Road",
        "city": "Balud",
        "country": "Philippines",
        "phone_number": "812-481-9967"
    },
    {
        "user_id": 192,
        "first_name": "Lora",
        "last_name": "Devey",
        "email": "ldevey5b@miitbeian.gov.cn",
        "gender": "Non-binary",
        "birthdate": "1/3/1997",
        "address": "36142 Bartillon Pass",
        "city": "Wangcheng",
        "country": "China",
        "phone_number": "496-709-6506"
    },
    {
        "user_id": 193,
        "first_name": "Fernandina",
        "last_name": "Grimestone",
        "email": "fgrimestone5c@ucoz.ru",
        "gender": "Genderfluid",
        "birthdate": "7/28/1964",
        "address": "231 Hintze Pass",
        "city": "Vargön",
        "country": "Sweden",
        "phone_number": "661-922-0431"
    },
    {
        "user_id": 194,
        "first_name": "Marion",
        "last_name": "Joslow",
        "email": "mjoslow5d@ed.gov",
        "gender": "Male",
        "birthdate": "4/26/1968",
        "address": "176 Ramsey Crossing",
        "city": "Kolç",
        "country": "Albania",
        "phone_number": "820-820-1809"
    },
    {
        "user_id": 195,
        "first_name": "Lemuel",
        "last_name": "Mashal",
        "email": "lmashal5e@reference.com",
        "gender": "Male",
        "birthdate": "8/6/1970",
        "address": "224 Mallard Parkway",
        "city": "Al ‘Awjā",
        "country": "Palestinian Territory",
        "phone_number": "233-761-4098"
    },
    {
        "user_id": 196,
        "first_name": "Giffy",
        "last_name": "Maberley",
        "email": "gmaberley5f@about.com",
        "gender": "Male",
        "birthdate": "10/16/1991",
        "address": "365 5th Trail",
        "city": "Nowy Dwór Mazowiecki",
        "country": "Poland",
        "phone_number": "270-913-2666"
    },
    {
        "user_id": 197,
        "first_name": "Vite",
        "last_name": "Jiles",
        "email": "vjiles5g@deviantart.com",
        "gender": "Male",
        "birthdate": "3/13/1982",
        "address": "3626 Porter Street",
        "city": "Shigu",
        "country": "China",
        "phone_number": "565-366-7484"
    },
    {
        "user_id": 198,
        "first_name": "Sada",
        "last_name": "Picott",
        "email": "spicott5h@pcworld.com",
        "gender": "Female",
        "birthdate": "2/28/1959",
        "address": "67 Swallow Crossing",
        "city": "Järfälla",
        "country": "Sweden",
        "phone_number": "671-638-9112"
    },
    {
        "user_id": 199,
        "first_name": "Bealle",
        "last_name": "Seale",
        "email": "bseale5i@de.vu",
        "gender": "Male",
        "birthdate": "5/8/1963",
        "address": "06817 Clyde Gallagher Lane",
        "city": "Amarete",
        "country": "Bolivia",
        "phone_number": "312-368-9401"
    },
    {
        "user_id": 200,
        "first_name": "Clari",
        "last_name": "Grabeham",
        "email": "cgrabeham5j@stanford.edu",
        "gender": "Female",
        "birthdate": "7/9/1994",
        "address": "77 Armistice Place",
        "city": "Vitória da Conquista",
        "country": "Brazil",
        "phone_number": "303-777-9803"
    }
]